tesci/__init__.py
tesci/release.py
tesci/similarity.py
tesci/transformations.py
tesci/types.py
tesci/scripts/__init__.py
tesci/scripts/context.py
tesci/scripts/tesci.py
tesci/scripts/aggregate/__init__.py
tesci/scripts/apply/__init__.py
tesci/scripts/include/__init__.py
tesci/scripts/join/__init__.py
tesci/scripts/preview/__init__.py
tesci/scripts/release/__init__.py
tesci/scripts/similarity/__init__.py
tesci/scripts/start/__init__.py
tesci-1.0.1.dist-info/LICENSE-APACHE
tesci-1.0.1.dist-info/LICENSE-MIT
tesci-1.0.1.dist-info/METADATA
tesci-1.0.1.dist-info/WHEEL
tesci-1.0.1.dist-info/entry_points.txt
tesci-1.0.1.dist-info/top_level.txt
tesci-1.0.1.dist-info/RECORD
