Metadata-Version: 2.1
Name: tesci
Version: 1.0.1
Summary: A toolkit to aid in scientific mapping
Keywords: scientific mapping,merging data sources
Classifier: Development Status :: 3 - Alpha
Classifier: Intended Audience :: Developers
Classifier: Intended Audience :: Information Technology
Classifier: Intended Audience :: Science/Research
Classifier: Topic :: Scientific/Engineering
Classifier: License :: OSI Approved :: MIT License
Classifier: License :: OSI Approved :: Apache Software License
Classifier: Natural Language :: English
Classifier: Programming Language :: Python :: 3.11
Classifier: Programming Language :: Python :: 3.12
Classifier: Operating System :: OS Independent
Requires-Python: >=3.11
License-File: LICENSE-APACHE
License-File: LICENSE-MIT
Requires-Dist: click >=8.1
Requires-Dist: requests
Requires-Dist: pandas
Requires-Dist: pyyaml
Requires-Dist: PyGithub >=2.1.1
Requires-Dist: attrs
Requires-Dist: xlrd
Requires-Dist: openpyxl
Requires-Dist: rapidfuzz >=3.5.2
Requires-Dist: importlib-metadata ; python_version < "3.8"
